<?xml version="1.0"?>
<ROOT>
	<FUNCTION_INFORMATION>
		<VHDL_LIBRARY NAME="altera_mf.altera_mf_components" />
		<HAS_SIM_LIB VALUE="ON" />
	</FUNCTION_INFORMATION>
	<PARAMETERS>
		<PARAMETER NAME="WIDTHAD" TYPE="INTEGER" />
		<PARAMETER NAME="WIDTH" TYPE="INTEGER" />
		<PARAMETER NAME="MAXIMUM_DEPTH" TYPE="INTEGER" DEFAULT_VALUE="0" />
		<PARAMETER NAME="NUMWORDS" TYPE="INTEGER" DEFAULT_VALUE="2 exp widthad" />
		<PARAMETER NAME="RDCONTROL_ACLR_B" TYPE="STRING" VALUE="ON" DEFAULT_VALUE_INDEX="0" />
		<PARAMETER NAME="RDCONTROL_REG_A" TYPE="STRING" VALUE="INCLOCK" DEFAULT_VALUE_INDEX="0" />
		<PARAMETER NAME="RDADDRESS_ACLR_A" TYPE="STRING" VALUE="ON" DEFAULT_VALUE_INDEX="0" />
		<PARAMETER NAME="RDADDRESS_REG_A" TYPE="STRING" VALUE="INCLOCK" DEFAULT_VALUE_INDEX="0" />
		<PARAMETER NAME="RDADDRESS_ACLR_B" TYPE="STRING" VALUE="ON" DEFAULT_VALUE_INDEX="0" />
		<PARAMETER NAME="OUTDATA_REG_A" TYPE="STRING" VALUE="OUTCLOCK" DEFAULT_VALUE_INDEX="0" />
		<PARAMETER NAME="RDADDRESS_REG_B" TYPE="STRING" VALUE="INCLOCK" DEFAULT_VALUE_INDEX="0" />
		<PARAMETER NAME="WRITE_REG" TYPE="STRING" VALUE="INCLOCK" DEFAULT_VALUE_INDEX="0" />
		<PARAMETER NAME="INDATA_REG" TYPE="STRING" VALUE="INCLOCK" DEFAULT_VALUE_INDEX="0" />
		<PARAMETER NAME="USE_EAB" TYPE="STRING" VALUE="ON" DEFAULT_VALUE_INDEX="0" CONTEXT="SYNTH_ONLY" />
		<PARAMETER NAME="INDATA_ACLR" TYPE="STRING" VALUE="ON" DEFAULT_VALUE_INDEX="0" />
		<PARAMETER NAME="RDCONTROL_ACLR_A" TYPE="STRING" VALUE="ON" DEFAULT_VALUE_INDEX="0" />
		<PARAMETER NAME="RDCONTROL_REG_B" TYPE="STRING" VALUE="INCLOCK" DEFAULT_VALUE_INDEX="0" />
		<PARAMETER NAME="INTENDED_DEVICE_FAMILY" TYPE="STRING" />
		<PARAMETER NAME="RAM_BLOCK_TYPE" TYPE="STRING" VALUE="AUTO" DEFAULT_VALUE_INDEX="0" />
		<PARAMETER NAME="LPM_FILE" TYPE="STRING" VALUE="UNUSED" DEFAULT_VALUE_INDEX="0" />
		<PARAMETER NAME="OUTDATA_ACLR_A" TYPE="STRING" VALUE="ON" DEFAULT_VALUE_INDEX="0" />
		<PARAMETER NAME="OUTDATA_REG_B" TYPE="STRING" VALUE="OUTCLOCK" DEFAULT_VALUE_INDEX="0" />
		<PARAMETER NAME="OUTDATA_ACLR_B" TYPE="STRING" VALUE="ON" DEFAULT_VALUE_INDEX="0" />
		<PARAMETER NAME="WRITE_ACLR" TYPE="STRING" VALUE="ON" DEFAULT_VALUE_INDEX="0" />
		<PARAMETER NAME="LPM_HINT" TYPE="STRING" VALUE="UNUSED" />
		<PARAMETER NAME="LPM_TYPE" TYPE="STRING" VALUE="alt3pram" />
	</PARAMETERS>
	<PORTS>
		<PORT NAME="rdaddress_b" TYPE="INPUT" WIDTH="WIDTHAD" />
		<PORT NAME="aclr" TYPE="INPUT" DEFAULT_VALUE="0" />
		<PORT NAME="outclocken" TYPE="INPUT" DEFAULT_VALUE="1" />
		<PORT NAME="inclocken" TYPE="INPUT" DEFAULT_VALUE="1" />
		<PORT NAME="rden_a" TYPE="INPUT" DEFAULT_VALUE="1" />
		<PORT NAME="rdaddress_a" TYPE="INPUT" WIDTH="WIDTHAD" />
		<PORT NAME="wraddress" TYPE="INPUT" WIDTH="WIDTHAD" />
		<PORT NAME="outclock" TYPE="INPUT" DEFAULT_VALUE="1" SIM_DEFAULT_VALUE="0" />
		<PORT NAME="data" TYPE="INPUT" WIDTH="WIDTH" />
		<PORT NAME="wren" TYPE="INPUT" SIM_DEFAULT_VALUE="0" />
		<PORT NAME="inclock" TYPE="INPUT" DEFAULT_VALUE="1" SIM_DEFAULT_VALUE="0" />
		<PORT NAME="rden_b" TYPE="INPUT" DEFAULT_VALUE="1" />
		<PORT NAME="qa" TYPE="OUTPUT" WIDTH="WIDTH" />
		<PORT NAME="qb" TYPE="OUTPUT" WIDTH="WIDTH" />
	</PORTS>
</ROOT>
