<?xml version="1.0"?>
<ROOT>
	<FUNCTION_INFORMATION>
		<HAS_SIM_LIB VALUE="ON" />
	</FUNCTION_INFORMATION>
	<PARAMETERS>
		<PARAMETER NAME="init_data" TYPE="Vector" DEFAULT_VALUE="0" WIDTH="0..127" />
		<PARAMETER NAME="LPM_TYPE" TYPE="STRING" VALUE="hardcopyiv_otp" />
		<PARAMETER NAME="data_width" TYPE="INTEGER" VALUE="128" CONTEXT="SIM_ONLY" />
		<PARAMETER NAME="init_file" TYPE="STRING" VALUE="init_file.hex" DEFAULT_VALUE_INDEX="0" CONTEXT="SIM_ONLY" />
		<PARAMETER NAME="lpm_hint" TYPE="STRING" VALUE="true" DEFAULT_VALUE_INDEX="0" />
	</PARAMETERS>
	<PORTS>
		<PORT NAME="otpclk" TYPE="INPUT" DEFAULT_VALUE="0" />
		<PORT NAME="otpclken" TYPE="INPUT" DEFAULT_VALUE="1" />
		<PORT NAME="otpshiftnld" TYPE="INPUT" DEFAULT_VALUE="0" />
		<PORT NAME="otpdout" TYPE="OUTPUT" DEFAULT_VALUE="0" />
	</PORTS>
</ROOT>
