<?xml version="1.0" encoding="UTF-8" ?>
<ROOT NAME="hardcopyiii_physical_lvds_clk_mux">
	<PARAMETERS>
		<PARAMETER NAME="LPM_TYPE" TYPE="STRING" VALUE="hardcopyiii_physical_lvds_clk_mux" />
	</PARAMETERS>
	<PORTS>
		<PORT NAME="lvdsfb_b" TYPE="INPUT" DEFAULT_VALUE="0"/>
		<PORT NAME="lvdsfb_t" TYPE="INPUT" DEFAULT_VALUE="0"/>
		<PORT NAME="dpaph_b" TYPE="INPUT" WIDTH="8" DEFAULT_VALUE="0"/>
		<PORT NAME="dpaph_t" TYPE="INPUT" WIDTH="8" DEFAULT_VALUE="0"/>
		<PORT NAME="loaden_b" TYPE="INPUT" WIDTH="2" DEFAULT_VALUE="0"/>
		<PORT NAME="loaden_t" TYPE="INPUT" WIDTH="2" DEFAULT_VALUE="0"/>
		<PORT NAME="sclk_b" TYPE="INPUT" WIDTH="2" DEFAULT_VALUE="0"/>
		<PORT NAME="sclk_t" TYPE="INPUT" WIDTH="2" DEFAULT_VALUE="0"/>
		<PORT NAME="fb_b" TYPE="OUTPUT" DEFAULT_VALUE="0"/>
		<PORT NAME="fb_t" TYPE="OUTPUT" DEFAULT_VALUE="0"/>
		<PORT NAME="dpaclk_b" TYPE="OUTPUT" WIDTH="8" DEFAULT_VALUE="0"/>
		<PORT NAME="dpaclk_t" TYPE="OUTPUT" WIDTH="8" DEFAULT_VALUE="0"/>
		<PORT NAME="fclk_b" TYPE="OUTPUT" WIDTH="4" DEFAULT_VALUE="0"/>
		<PORT NAME="fclk_t" TYPE="OUTPUT" WIDTH="4" DEFAULT_VALUE="0"/>
		<PORT NAME="lden_b" TYPE="OUTPUT" WIDTH="4" DEFAULT_VALUE="0"/>
		<PORT NAME="lden_t" TYPE="OUTPUT" WIDTH="4" DEFAULT_VALUE="0"/>
	</PORTS>
</ROOT>
